dicodon_optimizer/__init__.py
dicodon_optimizer/dicodon_optimization.py
dicodon_optimizer/fasta.py
dicodon_optimizer/hmm.py
dicodon_optimizer-0.1.1.dist-info/AUTHORS.rst
dicodon_optimizer-0.1.1.dist-info/LICENSE.txt
dicodon_optimizer-0.1.1.dist-info/METADATA
dicodon_optimizer-0.1.1.dist-info/WHEEL
dicodon_optimizer-0.1.1.dist-info/top_level.txt
dicodon_optimizer-0.1.1.dist-info/RECORD
