Metadata-Version: 2.1
Name: dicodon-optimizer
Version: 0.1.1
Summary: Dicodon optimization library
Home-page: https://github.com/pyscaffold/pyscaffold/
Author: Florian Finkernagel
Author-email: finkernagel@imt.uni-marburg.de
License: MIT
Project-URL: Documentation, https://pyscaffold.org/
Platform: any
Classifier: Development Status :: 4 - Beta
Classifier: Programming Language :: Python
Requires-Dist: importlib-metadata ; python_version < "3.8"
Provides-Extra: testing
Requires-Dist: pytest ; extra == 'testing'
Requires-Dist: pytest-cov ; extra == 'testing'
Requires-Dist: setuptools ; extra == 'testing'
